sdmxthon/__init__.py
sdmxthon/__version__.py
sdmxthon/api/api.py
sdmxthon/model/__init__.py
sdmxthon/model/base.py
sdmxthon/model/component.py
sdmxthon/model/dataset.py
sdmxthon/model/definitions.py
sdmxthon/model/descriptors.py
sdmxthon/model/error.py
sdmxthon/model/extras.py
sdmxthon/model/header.py
sdmxthon/model/itemScheme.py
sdmxthon/model/message.py
sdmxthon/model/representation.py
sdmxthon/model/submission.py
sdmxthon/model/utils.py
sdmxthon/parsers/__init__.py
sdmxthon/parsers/data_read.py
sdmxthon/parsers/data_validations.py
sdmxthon/parsers/metadata_read.py
sdmxthon/parsers/read.py
sdmxthon/parsers/reader_input_processor.py
sdmxthon/parsers/write.py
sdmxthon/parsers/writer_aux.py
sdmxthon/schemas/SDMXCommon.xsd
sdmxthon/schemas/SDMXCommonReferences.xsd
sdmxthon/schemas/SDMXDataGeneric.xsd
sdmxthon/schemas/SDMXDataGenericBase.xsd
sdmxthon/schemas/SDMXDataGenericTimeSeries.xsd
sdmxthon/schemas/SDMXDataStructureSpecific.xsd
sdmxthon/schemas/SDMXDataStructureSpecificBase.xsd
sdmxthon/schemas/SDMXDataStructureSpecificTimeSeries.xsd
sdmxthon/schemas/SDMXMessage.xsd
sdmxthon/schemas/SDMXMessageFooter.xsd
sdmxthon/schemas/SDMXMetadataGeneric.xsd
sdmxthon/schemas/SDMXMetadataStructureSpecific.xsd
sdmxthon/schemas/SDMXQuery.xsd
sdmxthon/schemas/SDMXQueryBase.xsd
sdmxthon/schemas/SDMXQueryCategorisation.xsd
sdmxthon/schemas/SDMXQueryCategory.xsd
sdmxthon/schemas/SDMXQueryCodelist.xsd
sdmxthon/schemas/SDMXQueryConcept.xsd
sdmxthon/schemas/SDMXQueryConstraint.xsd
sdmxthon/schemas/SDMXQueryData.xsd
sdmxthon/schemas/SDMXQueryDataStructure.xsd
sdmxthon/schemas/SDMXQueryDataflow.xsd
sdmxthon/schemas/SDMXQueryHierarchicalCodelist.xsd
sdmxthon/schemas/SDMXQueryMetadata.xsd
sdmxthon/schemas/SDMXQueryMetadataStructure.xsd
sdmxthon/schemas/SDMXQueryMetadataflow.xsd
sdmxthon/schemas/SDMXQueryOrganisation.xsd
sdmxthon/schemas/SDMXQueryProcess.xsd
sdmxthon/schemas/SDMXQueryProvisionAgreement.xsd
sdmxthon/schemas/SDMXQueryReportingTaxonomy.xsd
sdmxthon/schemas/SDMXQuerySchema.xsd
sdmxthon-2.6.8.dist-info/METADATA
sdmxthon-2.6.8.dist-info/WHEEL
sdmxthon-2.6.8.dist-info/top_level.txt
sdmxthon-2.6.8.dist-info/RECORD
