Metadata-Version: 2.4
Name: sdmxthon
Version: 2.6.8
Summary: Library with SDMX to Pandas, Pandas to SDMX, SDMX validation and SDMX metadata validation
Author: Francisco Javier Hernandez del Cano
Author-email: javier.hernandez@meaningfuldata.eu
License: Apache 2.0
Project-URL: Bug Tracker, https://github.com/Meaningful-Data/sdmxthon/issues
Project-URL: Documentation, https://docs.sdmxthon.meaningfuldata.eu
Project-URL: Source Code, https://github.com/Meaningful-Data/sdmxthon
Project-URL: Changelog, https://github.com/Meaningful-Data/sdmxthon/blob/master/Changelog.rst 
Keywords: SDMX,Pandas,Validation
Classifier: Development Status :: 4 - Beta
Classifier: Intended Audience :: Developers
Classifier: Topic :: Software Development
Classifier: License :: OSI Approved :: MIT License
Classifier: Programming Language :: Python :: 3
Classifier: Programming Language :: Python :: 3.7
Classifier: Programming Language :: Python :: 3.8
Classifier: Programming Language :: Python :: 3.9
Requires-Dist: lxml
Requires-Dist: pandas
Requires-Dist: numpy
Requires-Dist: validators
Requires-Dist: requests
Requires-Dist: xmltodict
Dynamic: author
Dynamic: author-email
Dynamic: classifier
Dynamic: description
Dynamic: description-content-type
Dynamic: keywords
Dynamic: license
Dynamic: project-url
Dynamic: requires-dist
Dynamic: summary
